function_tools/__init__.py
function_tools/app_settings.py
function_tools/apps.py
function_tools/caches.py
function_tools/consts.py
function_tools/decorators.py
function_tools/enums.py
function_tools/errors.py
function_tools/functions.py
function_tools/general.py
function_tools/helpers.py
function_tools/managers.py
function_tools/mixins.py
function_tools/models.py
function_tools/presenters.py
function_tools/receivers.py
function_tools/results.py
function_tools/runners.py
function_tools/storages.py
function_tools/strategies.py
function_tools/strings.py
function_tools/types.py
function_tools/utils.py
function_tools/validators.py
function_tools/function_templates/__init__.py
function_tools/function_templates/function_sync_template/README.md
function_tools/function_templates/function_sync_template/__init__.py-tpl
function_tools/function_templates/function_sync_template/apps.py-tpl
function_tools/function_templates/function_sync_template/caches.py-tpl
function_tools/function_templates/function_sync_template/consts.py-tpl
function_tools/function_templates/function_sync_template/enums.py-tpl
function_tools/function_templates/function_sync_template/errors.py-tpl
function_tools/function_templates/function_sync_template/functions.py-tpl
function_tools/function_templates/function_sync_template/helpers.py-tpl
function_tools/function_templates/function_sync_template/managers.py-tpl
function_tools/function_templates/function_sync_template/presenters.py-tpl
function_tools/function_templates/function_sync_template/results.py-tpl
function_tools/function_templates/function_sync_template/runners.py-tpl
function_tools/function_templates/function_sync_template/strings.py-tpl
function_tools/function_templates/function_sync_template/tests.py-tpl
function_tools/function_templates/function_sync_template/validators.py-tpl
function_tools/management/__init__.py
function_tools/management/consts.py
function_tools/management/commands/__init__.py
function_tools-1.10.4.dist-info/LICENSE
function_tools-1.10.4.dist-info/METADATA
function_tools-1.10.4.dist-info/WHEEL
function_tools-1.10.4.dist-info/top_level.txt
function_tools-1.10.4.dist-info/RECORD
