Metadata-Version: 2.1
Name: function-tools
Version: 1.10.4
Summary: Tools for creating functions
Author-email: Alexander Danilenko <a.danilenko@bars.group>
Classifier: Development Status :: 5 - Production/Stable
Classifier: License :: OSI Approved :: Apache Software License
Classifier: Programming Language :: Python :: 3
Classifier: Programming Language :: Python :: 3.9
Classifier: Programming Language :: Python :: 3.10
Classifier: Programming Language :: Python :: 3.11
Classifier: Programming Language :: Python :: 3.12
Classifier: Intended Audience :: Developers
Classifier: Environment :: Web Environment
Requires-Python: >=3.9
License-File: LICENSE
Requires-Dist: Django>=1.11.29
Requires-Dist: Pygments>=2.5.2
Requires-Dist: m3-db-utils<1,>=0.4
Requires-Dist: m3-django-compat<2,>=1.10.2
Requires-Dist: isort==5.12.0
Requires-Dist: ruff==0.6.9
Requires-Dist: sphinx<7.5,>=7
Requires-Dist: sphinx-autodoc-typehints<2.5,>=2
Requires-Dist: myst-parser<3.2,>=3
Requires-Dist: sphinx-design<0.7,>=0.6
